quill/character.py
quill/cli.py
quill/command_parser.py
quill/engine.py
quill/game_loader.py
quill/item.py
quill/player.py
quill/scene.py
quill/ui/console.py
quill/ui/dialogue_ui.py
quill/ui/inventory_ui.py
quill/ui/text_effects.py
quill/utils/ascii_art.py
quill/utils/game_creator.py
quill/utils/logger.py
quill/utils/spinner.py
quill_sdk-0.3.1.dist-info/LICENSE
quill_sdk-0.3.1.dist-info/METADATA
quill_sdk-0.3.1.dist-info/WHEEL
quill_sdk-0.3.1.dist-info/entry_points.txt
quill_sdk-0.3.1.dist-info/RECORD
