Metadata-Version: 2.3
Name: quill-sdk
Version: 0.3.1
Summary: A text-based adventure game engine with natural language processing
License: MIT
Keywords: game,text-adventure,interactive-fiction,education
Author: Timothy Pidashev
Author-email: pidashev.tim@gmail.com
Requires-Python: >=3.8,<4.0
Classifier: Development Status :: 3 - Alpha
Classifier: Intended Audience :: Education
Classifier: License :: OSI Approved :: MIT License
Classifier: Programming Language :: Python :: 3
Classifier: Programming Language :: Python :: 3.8
Classifier: Programming Language :: Python :: 3.9
Classifier: Programming Language :: Python :: 3.10
Classifier: Programming Language :: Python :: 3.11
Classifier: Programming Language :: Python :: 3.12
Classifier: Programming Language :: Python :: 3.13
Classifier: Topic :: Games/Entertainment :: Role-Playing
Provides-Extra: neural
Requires-Dist: colorama (>=0.4.4,<0.5.0)
Requires-Dist: openai (>=1.65.4,<2.0.0)
Requires-Dist: pyyaml (>=6.0,<7.0)
Requires-Dist: torch (>=1.10.0,<2.0.0) ; extra == "neural"
Requires-Dist: transformers (>=4.20.0,<5.0.0) ; extra == "neural"
Project-URL: Repository, https://github.com/timmypidashev/quill
